antpm/__init__.py
tests/__init__.py
tests/test_antpm.py
antpm-0.0.1.dist-info/LICENSE.txt
antpm-0.0.1.dist-info/METADATA
antpm-0.0.1.dist-info/WHEEL
antpm-0.0.1.dist-info/top_level.txt
antpm-0.0.1.dist-info/RECORD
