Metadata-Version: 2.1
Name: antpm
Version: 0.0.1
Summary: the ant path matcher python version
Home-page: 
Author: cxiaoer
Author-email: chen_wen@hotmail.com
Classifier: Programming Language :: Python :: 3
Classifier: License :: OSI Approved :: MIT License
Classifier: Operating System :: OS Independent
License-File: LICENSE.txt
